napari_bbox/__init__.py
napari_bbox/_reader.py
napari_bbox/_utils.py
napari_bbox/_widget.py
napari_bbox/_writer.py
napari_bbox/napari.yaml
napari_bbox/_tests/__init__.py
napari_bbox/_tests/test_reader.py
napari_bbox/_tests/test_widget.py
napari_bbox/_tests/test_writer.py
napari_bbox/boundingbox/__init__.py
napari_bbox/boundingbox/napari_0_4_15/__init__.py
napari_bbox/boundingbox/napari_0_4_15/_bounding_box_constants.py
napari_bbox/boundingbox/napari_0_4_15/_bounding_box_list.py
napari_bbox/boundingbox/napari_0_4_15/_bounding_box_mouse_bindings.py
napari_bbox/boundingbox/napari_0_4_15/_bounding_box_utils.py
napari_bbox/boundingbox/napari_0_4_15/_bounding_boxes_key_bindings.py
napari_bbox/boundingbox/napari_0_4_15/_mesh.py
napari_bbox/boundingbox/napari_0_4_15/bounding_box.py
napari_bbox/boundingbox/napari_0_4_15/bounding_boxes.py
napari_bbox/boundingbox/napari_0_4_15/qt_bounding_box_control.py
napari_bbox/boundingbox/napari_0_4_15/vispy_bounding_box_layer.py
napari_bbox/boundingbox/napari_0_4_18/__init__.py
napari_bbox/boundingbox/napari_0_4_18/_bounding_box_constants.py
napari_bbox/boundingbox/napari_0_4_18/_bounding_box_list.py
napari_bbox/boundingbox/napari_0_4_18/_bounding_box_mouse_bindings.py
napari_bbox/boundingbox/napari_0_4_18/_bounding_box_utils.py
napari_bbox/boundingbox/napari_0_4_18/_bounding_boxes_key_bindings.py
napari_bbox/boundingbox/napari_0_4_18/_mesh.py
napari_bbox/boundingbox/napari_0_4_18/bounding_box.py
napari_bbox/boundingbox/napari_0_4_18/bounding_boxes.py
napari_bbox/boundingbox/napari_0_4_18/qt_bounding_box_control.py
napari_bbox/boundingbox/napari_0_4_18/vispy_bounding_box_layer.py
napari_bbox/boundingbox/napari_0_4_18/vispy_bounding_box_visual.py
napari_bbox/resources/__init__.py
napari_bbox/resources/_cube_icon.py
napari_bbox/resources/cube.svg
napari_bbox/resources/napari_0_4_17/__init__.py
napari_bbox/resources/napari_0_4_17/cube_button.qss
napari_bbox/resources/napari_0_4_18/__init__.py
napari_bbox_spfluo-0.1.0.dist-info/LICENSE
napari_bbox_spfluo-0.1.0.dist-info/METADATA
napari_bbox_spfluo-0.1.0.dist-info/WHEEL
napari_bbox_spfluo-0.1.0.dist-info/top_level.txt
napari_bbox_spfluo-0.1.0.dist-info/RECORD
