Metadata-Version: 2.1
Name: napari-bbox-spfluo
Version: 0.1.0
Summary: A new layer for bounding boxes in 2+ dimensions. Fork of napari-bbox for spfluo-app needs.
Author-email: David Bauer <dbauer@brc.hu>
License: 
Project-URL: Bug Tracker, https://github.com/bauerdavid/napari-bbox/issues
Project-URL: Documentation, https://github.com/bauerdavid/napari-bbox#README.md
Project-URL: Source Code, https://github.com/bauerdavid/napari-bbox
Project-URL: User Support, https://github.com/bauerdavid/napari-bbox/issues
Classifier: Development Status :: 2 - Pre-Alpha
Classifier: Framework :: napari
Classifier: Intended Audience :: Developers
Classifier: License :: OSI Approved :: BSD License
Classifier: Operating System :: OS Independent
Classifier: Programming Language :: Python
Classifier: Programming Language :: Python :: 3
Classifier: Programming Language :: Python :: 3 :: Only
Classifier: Programming Language :: Python :: 3.8
Classifier: Programming Language :: Python :: 3.9
Classifier: Programming Language :: Python :: 3.10
Classifier: Programming Language :: Python :: 3.11
Classifier: Programming Language :: Python :: 3.12
Classifier: Topic :: Scientific/Engineering :: Image Processing
Requires-Python: >=3.8
License-File: LICENSE
Requires-Dist: numpy
Requires-Dist: magicgui
Requires-Dist: qtpy
Requires-Dist: napari>=0.4.15
